architect_copilot-0.1.0.dist-info/licenses/LICENSE
architect_mcp/__init__.py
architect_mcp/main.py
architect_copilot-0.1.0.dist-info/METADATA
architect_copilot-0.1.0.dist-info/WHEEL
architect_copilot-0.1.0.dist-info/entry_points.txt
architect_copilot-0.1.0.dist-info/top_level.txt
architect_copilot-0.1.0.dist-info/RECORD
