Metadata-Version: 2.4
Name: architect-copilot
Version: 0.1.0
Summary: Architect Copilot MCP tool using Azure OpenAI and Search.
Author: Your Name
Requires-Python: >=3.7
License-File: LICENSE
Requires-Dist: mcp-server
Requires-Dist: openai
Requires-Dist: python-dotenv
Requires-Dist: azure-search-documents
Requires-Dist: azure-core
Dynamic: author
Dynamic: license-file
Dynamic: requires-dist
Dynamic: requires-python
Dynamic: summary
